perconeb/__init__.py
perconeb/core.py
perconeb-0.1.1.dist-info/LICENSE
perconeb-0.1.1.dist-info/METADATA
perconeb-0.1.1.dist-info/WHEEL
perconeb-0.1.1.dist-info/top_level.txt
perconeb-0.1.1.dist-info/RECORD
