Metadata-Version: 2.1
Name: perconeb
Version: 0.1.1
Summary: A tool for finding percolation pathways in crystals
Home-page: https://github.com/dembart/perconeb
Author: Artem Dembitskiy
Author-email: art.dembitskiy@gmail.com
License: UNKNOWN
Platform: UNKNOWN
Classifier: Programming Language :: Python :: 3.6
Classifier: Programming Language :: Python :: 3.7
Classifier: Programming Language :: Python :: 3.8
Classifier: Programming Language :: Python :: 3.9
Classifier: Programming Language :: Python :: 3.10
Classifier: Programming Language :: Python :: 3.11
Classifier: License :: OSI Approved :: MIT License
Classifier: Operating System :: OS Independent
License-File: LICENSE
Requires-Dist: ase
Requires-Dist: numpy
Requires-Dist: networkx
Requires-Dist: spglib
Requires-Dist: scipy
